{
  "animateLoading": true,
  "backgroundColor": "white",
  "borderColor": "transparent",
  "borderRadius": "{{appsmith.theme.borderRadius.appBorderRadius}}",
  "borderWidth": "0",
  "bottomRow": 12,
  "boxShadow": "{{appsmith.theme.boxShadow.appBoxShadow}}",
  "children": [
    {
      "accentColor": "{{appsmith.theme.colors.primaryColor}}",
      "borderRadius": "{{appsmith.theme.borderRadius.appBorderRadius}}",
      "boxShadow": "none",
      "canExtend": false,
      "containerStyle": "none",
      "detachFromLayout": true,
      "displayName": "Canvas",
      "dynamicBindingPathList": [
        {
          "key": "borderRadius"
        },
        {
          "key": "accentColor"
        }
      ],
      "hideCard": true,
      "isDeprecated": false,
      "isLoading": false,
      "isVisible": true,
      "key": "h4gemadmp6",
      "leftColumn": 0,
      "parentColumnSpace": 1,
      "parentId": "3r5chpo3hy",
      "parentRowSpace": 1,
      "renderMode": "CANVAS",
      "topRow": 0,
      "type": "CANVAS_WIDGET",
      "version": 1,
      "widgetId": "icqyh69hkq",
      "widgetName": "Canvas4"
    }
  ],
  "containerStyle": "card",
  "disablePropertyPane": true,
  "disallowCopy": true,
  "displayName": "Container",
  "dragDisabled": true,
  "dynamicBindingPathList": [
    {
      "key": "borderRadius"
    },
    {
      "key": "boxShadow"
    }
  ],
  "hideCard": false,
  "iconSVG": "/static/media/icon.1977dca3.svg",
  "isCanvas": true,
  "isDeletable": false,
  "isDeprecated": false,
  "isLoading": false,
  "isVisible": true,
  "key": "py7avpdvjk",
  "leftColumn": 0,
  "openParentPropertyPane": true,
  "parentId": "q3steju1rn",
  "renderMode": "CANVAS",
  "rightColumn": 64,
  "topRow": 0,
  "type": "CONTAINER_WIDGET",
  "version": 1,
  "widgetId": "3r5chpo3hy",
  "widgetName": "Container2"
}